firstcalculation/__init__.py
firstcalculation/operation.py
balafirstlibrary-0.0.1.dist-info/LICENCE.txt
balafirstlibrary-0.0.1.dist-info/METADATA
balafirstlibrary-0.0.1.dist-info/WHEEL
balafirstlibrary-0.0.1.dist-info/top_level.txt
balafirstlibrary-0.0.1.dist-info/RECORD
